blackholecalc/__init__.py
blackholecalc/accretion_disk.py
blackholecalc/constants.py
blackholecalc/event_horizon.py
blackholecalc/hawking_radiation.py
blackholecalc-0.1.0.dist-info/METADATA
blackholecalc-0.1.0.dist-info/WHEEL
blackholecalc-0.1.0.dist-info/top_level.txt
blackholecalc-0.1.0.dist-info/RECORD
