Metadata-Version: 2.4
Name: blackholecalc
Version: 0.1.0
Summary: A Python library for calculating Black Hole properties (Event Horizon, Hawking Radiation, Accretion).
Author-email: Aditya-Roy-oops <asrpcp7@gmail.com>
Project-URL: Homepage, https://github.com/aditya-roy-oops/blackholecalc
Classifier: Programming Language :: Python :: 3
Classifier: License :: OSI Approved :: MIT License
Classifier: Operating System :: OS Independent
Requires-Python: >=3.7
